zeuscloud_iamspy/__init__.py
zeuscloud_iamspy/cli.py
zeuscloud_iamspy/conditions.py
zeuscloud_iamspy/datatypes.py
zeuscloud_iamspy/iam.py
zeuscloud_iamspy/log_config.py
zeuscloud_iamspy/model.py
zeuscloud_iamspy/parse.py
zeuscloud_iamspy/utils.py
zeuscloud_iamspy-0.8.0.dist-info/LICENSE.md
zeuscloud_iamspy-0.8.0.dist-info/METADATA
zeuscloud_iamspy-0.8.0.dist-info/WHEEL
zeuscloud_iamspy-0.8.0.dist-info/entry_points.txt
zeuscloud_iamspy-0.8.0.dist-info/RECORD
